napalm_arubaoss/ArubaOS.py
napalm_arubaoss/__init__.py
napalm_arubaoss/helper/__init__.py
napalm_arubaoss/helper/base.py
napalm_arubaoss/helper/commit_config.py
napalm_arubaoss/helper/compare_config.py
napalm_arubaoss/helper/confirm_commit.py
napalm_arubaoss/helper/get_arp_table.py
napalm_arubaoss/helper/get_config.py
napalm_arubaoss/helper/get_facts.py
napalm_arubaoss/helper/get_interfaces.py
napalm_arubaoss/helper/get_interfaces_ip.py
napalm_arubaoss/helper/get_lldp_neighbors.py
napalm_arubaoss/helper/get_lldp_neighbors_detail.py
napalm_arubaoss/helper/get_mac_address_table.py
napalm_arubaoss/helper/get_ntp_servers.py
napalm_arubaoss/helper/get_ntp_stats.py
napalm_arubaoss/helper/get_route_to.py
napalm_arubaoss/helper/has_pending_commit.py
napalm_arubaoss/helper/is_alive.py
napalm_arubaoss/helper/load_merge_candidate.py
napalm_arubaoss/helper/load_replace_candidate.py
napalm_arubaoss/helper/ping.py
napalm_arubaoss/helper/rollback.py
napalm_arubaoss/helper/traceroute.py
napalm_arubaoss/helper/utils.py
napalm_arubaoss/utils/textfsm_templates/show_arp.tpl
napalm_arubaoss/utils/textfsm_templates/show_ip_route.tpl
napalm_arubaoss/utils/textfsm_templates/show_ipv6_route.tpl
test/__init__.py
test/unit/__init__.py
test/unit/conftest.py
test/unit/test_getters.py
napalm_arubaos_switch-0.2.0.dist-info/LICENSE
napalm_arubaos_switch-0.2.0.dist-info/METADATA
napalm_arubaos_switch-0.2.0.dist-info/WHEEL
napalm_arubaos_switch-0.2.0.dist-info/top_level.txt
napalm_arubaos_switch-0.2.0.dist-info/RECORD
