Metadata-Version: 2.1
Name: napalm-arubaos-switch
Version: 0.2.0
Summary: Napalm driver for ArubaOS Switches
Home-page: https://github.com/napalm-automation-community/napalm-arubaos-switch/
Author: Guillermo Cotone
Author-email: 15230109+gcotone@users.noreply.github.com
License: UNKNOWN
Platform: UNKNOWN
Classifier: Topic :: Utilities
Classifier: Programming Language :: Python :: 3
Classifier: Programming Language :: Python :: 3.5
Classifier: Programming Language :: Python :: 3.6
Classifier: Programming Language :: Python :: 3.7
Classifier: Programming Language :: Python :: 3.8
Classifier: Programming Language :: Python :: 3.9
Classifier: Operating System :: POSIX :: Linux
License-File: LICENSE
Requires-Dist: napalm (>=3.3.0)
Requires-Dist: netaddr
Requires-Dist: requests
Requires-Dist: textfsm (>=1.1.0)
Requires-Dist: urllib3
